annuaire_entreprises_py/__init__.py
annuaire_entreprises_py/client.py
annuaire_entreprises_py-0.2.0.dist-info/licenses/LICENSE
annuaire_entreprises_py-0.2.0.dist-info/METADATA
annuaire_entreprises_py-0.2.0.dist-info/WHEEL
annuaire_entreprises_py-0.2.0.dist-info/top_level.txt
annuaire_entreprises_py-0.2.0.dist-info/RECORD
