Metadata-Version: 2.4
Name: annuaire_entreprises_py
Version: 0.2.0
Summary: Client Python pour l'API Recherche d'Entreprises (https://www.data.gouv.fr/dataservices/api-recherche-dentreprises/)
Author-email: Quentin DUTEIL <quentinduteil@xalystudio.fr>
License: GPL-3.0-or-later
License-File: LICENSE
Requires-Dist: requests>=2.25.0
Dynamic: license-file
